<?xml version="1.0" encoding="utf-8" ?>
<dwsync>
<file name="Link.php" server="66.147.244.197//public_html/" local="129482174526533532" remote="129501944400000000" />
<file name="LinkQuery.php" server="66.147.244.197//public_html/" local="129482174524513416" remote="129501944400000000" />
<file name="LinkSet.php" server="66.147.244.197//public_html/" local="129482174523283346" remote="129501945000000000" />
<file name="Note.php" server="66.147.244.197//public_html/" local="129482174521953270" remote="129501945000000000" />
<file name="NoteSet.php" server="66.147.244.197//public_html/" local="129482174519853150" remote="129501945000000000" />
<file name="Tag.php" server="66.147.244.197//public_html/" local="129482174519063105" remote="129501945000000000" />
<file name="TagSet.php" server="66.147.244.197//public_html/" local="129482174517673025" remote="129501945000000000" />
<file name="Watchlist.php" server="66.147.244.197//public_html/" local="129482174518563076" remote="129501945000000000" />
<file name="WatchlistFilter.php" server="66.147.244.197//public_html/" local="129482174515232885" remote="129501945000000000" />
<file name="WatchlistFilterSet.php" server="66.147.244.197//public_html/" local="129482174513482785" remote="129501945000000000" />
<file name="WatchlistSet.php" server="66.147.244.197//public_html/" local="129482174514022816" remote="129501945000000000" />
</dwsync>